LICENSE.txt
LICENSES_bundled.txt
MANIFEST.in
Makefile
README.md
pyproject.toml
requirements-dev.txt
requirements.txt
setup.cfg
setup.py
setup_helpers.py
doc/Makefile
doc/conf.py
doc/index.rst
doc/related_implementations.rst
doc/sphinxext/docscrape.py
doc/sphinxext/docscrape_sphinx.py
doc/sphinxext/math_dollar.py
doc/sphinxext/numpydoc.py
doc/tools/LICENSE.txt
doc/tools/apigen.py
doc/tools/buildmodref.py
mrrt/__init__.py
mrrt.nufft.egg-info/PKG-INFO
mrrt.nufft.egg-info/SOURCES.txt
mrrt.nufft.egg-info/dependency_links.txt
mrrt.nufft.egg-info/requires.txt
mrrt.nufft.egg-info/top_level.txt
mrrt/nufft/__init__.py
mrrt/nufft/_cupy.py
mrrt/nufft/_dtft.py
mrrt/nufft/_interp_table.py
mrrt/nufft/_kaiser_bessel.py
mrrt/nufft/_kernels.py
mrrt/nufft/_nufft.py
mrrt/nufft/_utils.py
mrrt/nufft/version.py
mrrt/nufft/_extensions/__init__.py
mrrt/nufft/_extensions/_nufft_table.c
mrrt/nufft/_extensions/_nufft_table.pxd
mrrt/nufft/_extensions/_nufft_table.pyx
mrrt/nufft/_extensions/c/nufft_table.c
mrrt/nufft/_extensions/c/nufft_table.h
mrrt/nufft/_extensions/c/nufft_table.template.c
mrrt/nufft/_extensions/c/nufft_table.template.h
mrrt/nufft/_extensions/c/templating.h
mrrt/nufft/cuda/__init__.py
mrrt/nufft/cuda/cupy.py
mrrt/nufft/cuda/jinja/gridding_kernel_includes.jinja
mrrt/nufft/cuda/jinja/table_1d_adjoint.jinja
mrrt/nufft/cuda/jinja/table_1d_forward.jinja
mrrt/nufft/cuda/jinja/table_2d_adjoint.jinja
mrrt/nufft/cuda/jinja/table_2d_forward.jinja
mrrt/nufft/cuda/jinja/table_3d_adjoint.jinja
mrrt/nufft/cuda/jinja/table_3d_forward.jinja
mrrt/nufft/tests/__init__.py
mrrt/nufft/tests/test_dtft.py
mrrt/nufft/tests/test_kaiser.py
mrrt/nufft/tests/test_kernels.py
mrrt/nufft/tests/test_nufft.py
mrrt/nufft/tests/test_utils.py
mrrt/nufft/tests/data/nufft_gauss.npz
mrrt/nufft/tests/data/nufft_interp_zn.npz
requirements/default.txt
requirements/optional.txt
requirements/test.txt