Metadata-Version: 1.2
Name: mrrt.nufft
Version: 0.2.1
Summary: Non-uniform FFT in 1D, 2D and 3D for CPU and GPU (CUDA)
Home-page: http://github.com/mritools/mrrt.nufft
Author: Gregory R. Lee
Author-email: grlee77@gmail.com
Maintainer: Gregory R. Lee
Maintainer-email: grlee77@gmail.com
License: BSD
Keywords: non-uniform fast Fourier transform,NFFT,NUFFT,scientific,non-cartesian MRI,magnetic resonance imaging
Platform: OS Independent
Classifier: Development Status :: 4 - Beta
Classifier: Environment :: Console
Classifier: Intended Audience :: Science/Research
Classifier: License :: OSI Approved :: BSD License
Classifier: Operating System :: OS Independent
Classifier: Programming Language :: Python
Classifier: Programming Language :: Python :: 3
Classifier: Programming Language :: Python :: 3.6
Classifier: Programming Language :: Python :: 3.7
Classifier: Programming Language :: Python :: 3.8
Classifier: Programming Language :: Python :: 3 :: Only
Classifier: Programming Language :: Python :: Implementation :: CPython
Classifier: Topic :: Scientific/Engineering
Requires: numpy
Requires: cython
Requires: mrrt.utils
Requires-Python: >= 3.6
